kcwidrp/__init__.py
kcwidrp/configs/__init__.py
kcwidrp/configs/framework.cfg
kcwidrp/configs/kcwi.cfg
kcwidrp/configs/kcwi_koarti.cfg
kcwidrp/configs/logger.cfg
kcwidrp/configs/rti.cfg
kcwidrp/core/__init__.py
kcwidrp/core/bokeh_plotting.py
kcwidrp/core/geometric.py
kcwidrp/core/kcwi_correct_extin.py
kcwidrp/core/kcwi_get_std.py
kcwidrp/core/kcwi_plotting.py
kcwidrp/core/kcwi_proctab.py
kcwidrp/core/bspline/Bspline.py
kcwidrp/core/bspline/__init__.py
kcwidrp/core/bspline/math.py
kcwidrp/core/bspline/median.py
kcwidrp/core/bspline/misc.py
kcwidrp/core/bspline/trace.py
kcwidrp/core/bspline/uniq.py
kcwidrp/data/README.rst
kcwidrp/data/Untitled.ipynb
kcwidrp/data/__init__.py
kcwidrp/data/defect_ALL_1x1.dat
kcwidrp/data/defect_ALL_2x2.dat
kcwidrp/data/defect_L2U2L1U1_1x1.dat
kcwidrp/data/defect_L2U2_1x1.dat
kcwidrp/data/defect_L2U2_2x2.dat
kcwidrp/data/defect_TBO_1x1.dat
kcwidrp/data/defect_TBO_2x2.dat
kcwidrp/data/defect_TUP_1x1.dat
kcwidrp/data/defect_TUP_2x2.dat
kcwidrp/data/fear.fits
kcwidrp/data/fear_list.txt
kcwidrp/data/ohsky.fits
kcwidrp/data/thar.fits
kcwidrp/data/thar_list.txt
kcwidrp/data/extin/ReadMe
kcwidrp/data/extin/snfext.dat
kcwidrp/data/extin/snfext.fits
kcwidrp/data/stds/40erib.fits
kcwidrp/data/stds/40erib.png
kcwidrp/data/stds/bd02d3375.fits
kcwidrp/data/stds/bd02d3375.lmsk
kcwidrp/data/stds/bd02d3375.png
kcwidrp/data/stds/bd08d2015.fits
kcwidrp/data/stds/bd08d2015.png
kcwidrp/data/stds/bd17d4708.fits
kcwidrp/data/stds/bd17d4708.png
kcwidrp/data/stds/bd21d0607.fits
kcwidrp/data/stds/bd21d0607.png
kcwidrp/data/stds/bd25d3941.fits
kcwidrp/data/stds/bd25d3941.png
kcwidrp/data/stds/bd25d4655.fits
kcwidrp/data/stds/bd25d4655.png
kcwidrp/data/stds/bd26d2606.fits
kcwidrp/data/stds/bd26d2606.png
kcwidrp/data/stds/bd28d4211.fits
kcwidrp/data/stds/bd28d4211.png
kcwidrp/data/stds/bd29d2091.fits
kcwidrp/data/stds/bd29d2091.png
kcwidrp/data/stds/bd33d2642.fits
kcwidrp/data/stds/bd33d2642.png
kcwidrp/data/stds/bd40d4032.fits
kcwidrp/data/stds/bd40d4032.png
kcwidrp-1.2.0.dist-info/LICENSE.rst
kcwidrp-1.2.0.dist-info/METADATA
kcwidrp-1.2.0.dist-info/WHEEL
kcwidrp-1.2.0.dist-info/entry_points.txt
kcwidrp-1.2.0.dist-info/top_level.txt
kcwidrp-1.2.0.dist-info/RECORD
