Metadata-Version: 2.2
Name: kcwidrp
Version: 1.2.0
Summary: KCWI Data Reduction Pipeline
Home-page: https://github.com/Keck-DataReductionPipelines/KCWI_DRP.git
Author: J. Neill, L. Rizzi, M. Brodheim
Author-email: neill@srl.caltech.edu
License: BSD 3-Clause
Provides: k
Provides: c
Provides: w
Provides: i
Provides: d
Provides: r
Provides: p
Requires-Python: ~=3.12
License-File: LICENSE.rst
Requires-Dist: scikit-image~=0.24
Requires-Dist: astropy~=6.1.3
Requires-Dist: astroscrappy~=1.1.0
Requires-Dist: ccdproc~=2.4.2
Requires-Dist: numpy==1.26.4
Requires-Dist: scipy~=1.14.1
Requires-Dist: pyerfa
Requires-Dist: bokeh~=2.4.3
Requires-Dist: jinja2~=3.0.3
Requires-Dist: psutil~=5.7.0
Requires-Dist: pytest~=5.4.1
Requires-Dist: keckdrpframework
Requires-Dist: requests
Requires-Dist: pandas~=1.3.5
Requires-Dist: matplotlib~=3.9.2
Requires-Dist: ref_index~=1.0
Requires-Dist: pyregion~=2.0
Requires-Dist: cython
Requires-Dist: selenium
Requires-Dist: phantomjs
Dynamic: author
Dynamic: author-email
Dynamic: description
Dynamic: license
Dynamic: provides
Dynamic: requires-dist
Dynamic: requires-python
Dynamic: summary
